django_migrate_project-0.1.0.dist-info/RECORD
django_migrate_project-0.1.0.dist-info/top_level.txt
django_migrate_project-0.1.0.dist-info/WHEEL
django_migrate_project-0.1.0.dist-info/METADATA
django_migrate_project-0.1.0.dist-info/metadata.json
django_migrate_project-0.1.0.dist-info/DESCRIPTION.rst
django_migrate_project/__init__.py
django_migrate_project/management/__init__.py
django_migrate_project/management/commands/migrateproject.py
django_migrate_project/management/commands/collectmigrations.py
django_migrate_project/management/commands/__init__.py
