Metadata-Version: 2.0
Name: django-migrate-project
Version: 0.1.0
Summary: Django management commands for project-wide (editable) migrations.
Home-page: https://github.com/dsanders11/django-migrate-project/
Author: David Sanders
Author-email: dsanders11@ucsbalum.com
License: MIT
Keywords: django migration database
Platform: UNKNOWN
Classifier: Development Status :: 4 - Beta
Classifier: Environment :: Web Environment
Classifier: Framework :: Django
Classifier: Intended Audience :: Developers
Classifier: Intended Audience :: System Administrators
Classifier: License :: OSI Approved :: MIT License
Classifier: Operating System :: OS Independent
Classifier: Programming Language :: Python
Classifier: Programming Language :: Python :: 2.7
Classifier: Programming Language :: Python :: 3.2
Classifier: Programming Language :: Python :: 3.3
Classifier: Programming Language :: Python :: 3.4
Classifier: Topic :: Utilities
Classifier: Topic :: Database
Requires-Dist: Django (>1.7)
